{"singlePage": ["about"], "startSite": "01/16/2014", "filingNum": "", "onePageListNum": 10, "commentLabelColor": "#006b75", "yearColorList": ["#bc4c00", "#0969da", "#1f883d", "#A333D0"], "i18n": "CN", "themeMode": "manual", "dayTheme": "light", "nightTheme": "dark_colorblind", "urlMode": "pinyin", "script": "", "style": "", "indexScript": "", "indexStyle": "", "bottomText": "\u8f6c\u8f7d\u8bf7\u6ce8\u660e\u51fa\u5904", "showPostSource": "0", "iconList": {}, "UTC": 8, "rssSplit": "sentence", "exlink": {}, "title": "Nan0ok", "subTitle": "\u8981\u662f\u8ffd\u4e0d\u4e0a\u5149\uff0c\u90a3\u5c31\u53d8\u6210\u5149\u5427\u3002", "avatarUrl": "https://github.githubassets.com/favicons/favicon.svg", "GMEEK_VERSION": "last", "homeUrl": "https://blog.czbb.top", "email": "wangweinan1121@163.com", "postListJson": {"P1": {"htmlDir": "docs/post/di-yi-pian-bo-ke-2.html", "labels": ["bug"], "postTitle": "\u7b2c\u4e00\u7bc7\u535a\u5ba22", "postUrl": "post/di-yi-pian-bo-ke-2.html", "postSourceUrl": "https://github.com/czbb1993/czbb1993.github.io/issues/1", "commentNum": 0, "wordCount": 10, "description": "\u6d4b\u8bd5\u7528\r\n\u7b2c\u4e00\u7bc7\u535a\u5ba2\u3002", "top": 0, "createdAt": 1712503063, "style": "", "script": "", "ogImage": "https://github.githubassets.com/favicons/favicon.svg", "createdDate": "2024-04-07", "dateLabelColor": "#bc4c00"}, "P2": {"htmlDir": "docs/post/di-yi-ci-ce-shi-shi-bai.html", "labels": ["\u968f\u7b14"], "postTitle": "\u7b2c\u4e00\u6b21\u6d4b\u8bd5\u5931\u8d25", "postUrl": "post/di-yi-ci-ce-shi-shi-bai.html", "postSourceUrl": "https://github.com/czbb1993/czbb1993.github.io/issues/2", "commentNum": 0, "wordCount": 5, "description": "\u7b2c\u4e8c\u6b21\u6d4b\u8bd5\u3002", "top": 0, "createdAt": 1712503948, "style": "", "script": "", "ogImage": "https://github.githubassets.com/favicons/favicon.svg", "createdDate": "2024-04-07", "dateLabelColor": "#bc4c00"}}, "singeListJson": {}, "labelColorDict": {"bug": "#d73a4a", "documentation": "#0075ca", "duplicate": "#cfd3d7", "enhancement": "#a2eeef", "good first issue": "#7057ff", "help wanted": "#008672", "invalid": "#e4e669", "question": "#d876e3", "wontfix": "#ffffff", "\u968f\u7b14": "#bfdadc"}, "displayTitle": "Nan0ok", "faviconUrl": "https://github.githubassets.com/favicons/favicon.svg", "ogImage": "https://github.githubassets.com/favicons/favicon.svg", "prevUrl": "disabled", "nextUrl": "disabled"}